nwn_dg/__init__.py
nwn_dg/__main__.py
nwn_dg/app.py
nwn_dg/cli.py
nwn_dg/constants.py
nwn_dg/dungeon.py
nwn_dg/idungeon.py
nwn_dg/maze.py
nwn_dg/seed.py
nwn_dg/api/__init__.py
nwn_dg/api/health.py
nwn_dg/api/tilejson.py
nwn_dg/classes/__init__.py
nwn_dg/classes/cell.py
nwn_dg/classes/dimensions.py
nwn_dg/classes/position.py
nwn_dg/classes/room.py
nwn_dg/map_layouts/__init__.py
nwn_dg/map_layouts/box.py
nwn_dg/mixins/__init__.py
nwn_dg/mixins/deadend.py
nwn_dg/mixins/path.py
nwn_dg/mixins/reshape.py
nwn_dg/mixins/room.py
nwn_dg/mixins/transition.py
nwn_dg/mixins/tunnel.py
nwn_dg/outputs/__init__.py
nwn_dg/outputs/map_png.py
nwn_dg/outputs/tilejson.py
nwn_dg/outputs/tileset.py
nwn_dg/outputs/tree.py
nwn_dg/outputs/tilesets/__init__.py
nwn_dg/outputs/tilesets/tdc01.py
nwn_dg/room_layouts/__init__.py
nwn_dg/room_layouts/scattered.py
nwn_dg-0.4.1.dist-info/LICENSE
nwn_dg-0.4.1.dist-info/METADATA
nwn_dg-0.4.1.dist-info/WHEEL
nwn_dg-0.4.1.dist-info/entry_points.txt
nwn_dg-0.4.1.dist-info/top_level.txt
nwn_dg-0.4.1.dist-info/zip-safe
nwn_dg-0.4.1.dist-info/RECORD
