Metadata-Version: 2.1
Name: nwn_dg
Version: 0.4.1
Summary: Neverwinter Nights (nwn) dungeon generator
Author-email: Julien Lecomte <julien@lecomte.at>
License: MIT
Project-URL: Homepage, https://gitlab.com/cappysan/nwn-dg
Project-URL: Source code, https://gitlab.com/cappysan/nwn-dg
Project-URL: Bug tracker, https://gitlab.com/cappysan/nwn-dg/-/issues
Classifier: License :: OSI Approved :: MIT License
Classifier: Development Status :: 4 - Beta
Classifier: Programming Language :: Python :: 3 :: Only
Classifier: Programming Language :: Python :: 3.11
Classifier: Programming Language :: Python :: 3.12
Requires-Python: >=3.11
License-File: LICENSE
Requires-Dist: boltons
Requires-Dist: matplotlib
Requires-Dist: networkx
Requires-Dist: pycairo
Requires-Dist: torxtools
Provides-Extra: dev
Provides-Extra: api
Requires-Dist: connexion[swagger-ui,uvicorn]; extra == "api"
